{
    "url"    : "https://github.com/uboslinux/ubos-webtrees",
    "type"   : "git",
    "branch" : "${branch}",

    "channels" : [
        "red",
        "yellow"
    ],

    "packages" : {
        "webtrees" : {
            "archs" : [
                "armv7h",
                "aarch64",
                "x86_64"
            ]
        },
    },

    "remove-packages" : {
        "webtrees" : {
            "archs" : [
                "armv6h"
            ]
        }
    },

    "webapptests" : {
        "webtrees/tests/WebTreesTest1.pm" : {}
    }
}
